odoo/addons/ssi_l10n_id_taxform_bukti_potong_pph_f113304/README.rst
odoo/addons/ssi_l10n_id_taxform_bukti_potong_pph_f113304/__init__.py
odoo/addons/ssi_l10n_id_taxform_bukti_potong_pph_f113304/__manifest__.py
odoo/addons/ssi_l10n_id_taxform_bukti_potong_pph_f113304/data/account_journal_data.xml
odoo/addons/ssi_l10n_id_taxform_bukti_potong_pph_f113304/data/approval_template_data.xml
odoo/addons/ssi_l10n_id_taxform_bukti_potong_pph_f113304/data/ir_sequence_data.xml
odoo/addons/ssi_l10n_id_taxform_bukti_potong_pph_f113304/data/l10n_id_bukti_potong_type.xml
odoo/addons/ssi_l10n_id_taxform_bukti_potong_pph_f113304/data/policy_template_data.xml
odoo/addons/ssi_l10n_id_taxform_bukti_potong_pph_f113304/data/sequence_template_data.xml
odoo/addons/ssi_l10n_id_taxform_bukti_potong_pph_f113304/demo/account_account_demo.xml
odoo/addons/ssi_l10n_id_taxform_bukti_potong_pph_f113304/demo/account_journal_demo.xml
odoo/addons/ssi_l10n_id_taxform_bukti_potong_pph_f113304/demo/account_tax_demo.xml
odoo/addons/ssi_l10n_id_taxform_bukti_potong_pph_f113304/demo/l10n_id_bukti_potong_type_demo.xml
odoo/addons/ssi_l10n_id_taxform_bukti_potong_pph_f113304/models/__init__.py
odoo/addons/ssi_l10n_id_taxform_bukti_potong_pph_f113304/models/bukti_potong_pph_f113304_in.py
odoo/addons/ssi_l10n_id_taxform_bukti_potong_pph_f113304/models/bukti_potong_pph_f113304_in_line.py
odoo/addons/ssi_l10n_id_taxform_bukti_potong_pph_f113304/models/bukti_potong_pph_f113304_out.py
odoo/addons/ssi_l10n_id_taxform_bukti_potong_pph_f113304/models/bukti_potong_pph_f113304_out_line.py
odoo/addons/ssi_l10n_id_taxform_bukti_potong_pph_f113304/security/ir.model.access.csv
odoo/addons/ssi_l10n_id_taxform_bukti_potong_pph_f113304/security/ir_module_category_data.xml
odoo/addons/ssi_l10n_id_taxform_bukti_potong_pph_f113304/security/ir_rule_data.xml
odoo/addons/ssi_l10n_id_taxform_bukti_potong_pph_f113304/security/res_group_data.xml
odoo/addons/ssi_l10n_id_taxform_bukti_potong_pph_f113304/static/description/icon.png
odoo14_addon_ssi_l10n_id_taxform_bukti_potong_pph_f113304-14.0.1.6.0.dist-info/METADATA
odoo14_addon_ssi_l10n_id_taxform_bukti_potong_pph_f113304-14.0.1.6.0.dist-info/WHEEL
odoo14_addon_ssi_l10n_id_taxform_bukti_potong_pph_f113304-14.0.1.6.0.dist-info/top_level.txt
odoo14_addon_ssi_l10n_id_taxform_bukti_potong_pph_f113304-14.0.1.6.0.dist-info/RECORD
